streaming/__cli__.py
streaming/__init__.py
streaming/apps.py
streaming/callbacks.py
streaming/config.py
streaming/event.py
streaming/exceptions.py
streaming/manager.py
streaming/py.typed
streaming/types.py
streaming/utils.py
streaming/version.py
streaming/backends/__init__.py
streaming/backends/_base.py
streaming/backends/console.py
streaming/backends/debug.py
streaming/backends/rabbitmq.py
django_streaming-0.8.0.dist-info/METADATA
django_streaming-0.8.0.dist-info/WHEEL
django_streaming-0.8.0.dist-info/entry_points.txt
django_streaming-0.8.0.dist-info/licenses/LICENSE
django_streaming-0.8.0.dist-info/RECORD
