Metadata-Version: 2.4
Name: django-streaming
Version: 0.8.0
Summary: A project for streaming data.
Project-URL: Documentation, https://github.com/UNICEF/django-streaming
Project-URL: Homepage, https://github.com/UNICEF/django-streaming
Author-email: Stefano Apostolico <s.apostolico@gmail.com>
License-File: LICENSE
Classifier: Environment :: Web Environment
Classifier: Framework :: Django
Classifier: Framework :: Django :: 3.2
Classifier: Framework :: Django :: 4.2
Classifier: Framework :: Django :: 5.2
Classifier: Intended Audience :: Developers
Classifier: License :: OSI Approved :: MIT License
Classifier: Operating System :: OS Independent
Classifier: Programming Language :: Python :: 3 :: Only
Classifier: Programming Language :: Python :: 3.10
Classifier: Programming Language :: Python :: 3.11
Classifier: Programming Language :: Python :: 3.12
Classifier: Programming Language :: Python :: 3.13
Classifier: Topic :: Software Development :: Libraries :: Application Frameworks
Classifier: Topic :: Software Development :: Libraries :: Python Modules
Requires-Python: >=3.10
Requires-Dist: click>=8
Requires-Dist: colorama>=0.4.6
Requires-Dist: django-stubs-ext
Requires-Dist: django>=3
Requires-Dist: markdown>=3.8.2
Requires-Dist: pika>=1.3.2
Requires-Dist: requests>=2.32.5
